kuromon/__init__.py
kuromon/errors.py
kuromon/kuromon.py
kuromon-0.2.0.dist-info/LICENSE
kuromon-0.2.0.dist-info/WHEEL
kuromon-0.2.0.dist-info/METADATA
kuromon-0.2.0.dist-info/RECORD
