Metadata-Version: 2.1
Name: kuromon
Version: 0.2.0
Summary: Convert a list of dict, dataclass, Pydantic or POPO objects into a string represented table
Home-page: https://github.com/ninoseki/kuromon
Author: Manabu Niseki
Author-email: manabu.niseki@gmail.com
Requires-Python: >=3.7,<4.0
Classifier: Programming Language :: Python :: 3
Classifier: Programming Language :: Python :: 3.10
Classifier: Programming Language :: Python :: 3.7
Classifier: Programming Language :: Python :: 3.8
Classifier: Programming Language :: Python :: 3.9
Provides-Extra: pydantic
Requires-Dist: importlib-metadata (>=4.12.0,<5.0.0); python_version < "3.8"
Requires-Dist: pydantic (>=1.6.2,!=1.7,!=1.7.1,!=1.7.2,!=1.7.3,!=1.8,!=1.8.1,<2.0.0); extra == "pydantic"
Requires-Dist: tabulate (>=0.8.10,<0.9.0)
Project-URL: Repository, https://github.com/ninoseki/kuromon
